[
    {
        "tokens": [
            "But",
            "understand",
            "this:",
            "In",
            "the",
            "last",
            "days",
            "terrible",
            "times",
            "will",
            "come."
        ],
        "verse_reference": "2 Timothy 3:1",
        "book": "2 Timothy",
        "chapter": "3",
        "verse": "1"
    },
    {
        "tokens": [
            "For",
            "men",
            "will",
            "be",
            "lovers",
            "of",
            "themselves,",
            "lovers",
            "of",
            "money,",
            "boastful,",
            "arrogant,",
            "abusive,",
            "disobedient",
            "to",
            "their",
            "parents,",
            "ungrateful,",
            "unholy,"
        ],
        "verse_reference": "2 Timothy 3:2",
        "book": "2 Timothy",
        "chapter": "3",
        "verse": "2"
    },
    {
        "tokens": [
            "unloving,",
            "unforgiving,",
            "slanderous,",
            "without",
            "self-control,",
            "brutal,",
            "without",
            "love",
            "of",
            "good,"
        ],
        "verse_reference": "2 Timothy 3:3",
        "book": "2 Timothy",
        "chapter": "3",
        "verse": "3"
    },
    {
        "tokens": [
            "traitorous,",
            "reckless,",
            "conceited,",
            "lovers",
            "of",
            "pleasure",
            "rather",
            "than",
            "lovers",
            "of",
            "God,"
        ],
        "verse_reference": "2 Timothy 3:4",
        "book": "2 Timothy",
        "chapter": "3",
        "verse": "4"
    },
    {
        "tokens": [
            "having",
            "a",
            "form",
            "of",
            "godliness",
            "but",
            "denying",
            "its",
            "power.",
            "Turn",
            "away",
            "from",
            "such",
            "as",
            "these!"
        ],
        "verse_reference": "2 Timothy 3:5",
        "book": "2 Timothy",
        "chapter": "3",
        "verse": "5"
    },
    {
        "tokens": [
            "They",
            "are",
            "the",
            "kind",
            "who",
            "worm",
            "their",
            "way",
            "into",
            "households",
            "and",
            "captivate",
            "vulnerable",
            "women",
            "who",
            "are",
            "weighed",
            "down",
            "with",
            "sins",
            "and",
            "led",
            "astray",
            "by",
            "various",
            "passions,"
        ],
        "verse_reference": "2 Timothy 3:6",
        "book": "2 Timothy",
        "chapter": "3",
        "verse": "6"
    },
    {
        "tokens": [
            "who",
            "are",
            "always",
            "learning",
            "but",
            "never",
            "able",
            "to",
            "come",
            "to",
            "a",
            "knowledge",
            "of",
            "the",
            "truth."
        ],
        "verse_reference": "2 Timothy 3:7",
        "book": "2 Timothy",
        "chapter": "3",
        "verse": "7"
    },
    {
        "tokens": [
            "Just",
            "as",
            "Jannes",
            "and",
            "Jambres",
            "opposed",
            "Moses,",
            "so",
            "also",
            "these",
            "men",
            "oppose",
            "the",
            "truth.",
            "They",
            "are",
            "depraved",
            "in",
            "mind",
            "and",
            "disqualified",
            "from",
            "the",
            "faith."
        ],
        "verse_reference": "2 Timothy 3:8",
        "book": "2 Timothy",
        "chapter": "3",
        "verse": "8"
    },
    {
        "tokens": [
            "But",
            "they",
            "will",
            "not",
            "advance",
            "much",
            "further.",
            "For",
            "just",
            "like",
            "Jannes",
            "and",
            "Jambres,",
            "their",
            "folly",
            "will",
            "be",
            "plain",
            "to",
            "everyone."
        ],
        "verse_reference": "2 Timothy 3:9",
        "book": "2 Timothy",
        "chapter": "3",
        "verse": "9"
    },
    {
        "tokens": [
            "You,",
            "however,",
            "have",
            "observed",
            "my",
            "teaching,",
            "my",
            "conduct,",
            "my",
            "purpose,",
            "my",
            "faith,",
            "my",
            "patience,",
            "my",
            "love,",
            "my",
            "perseverance,"
        ],
        "verse_reference": "2 Timothy 3:10",
        "book": "2 Timothy",
        "chapter": "3",
        "verse": "10"
    },
    {
        "tokens": [
            "my",
            "persecutions,",
            "and",
            "the",
            "sufferings",
            "that",
            "came",
            "upon",
            "me",
            "in",
            "Antioch,",
            "Iconium,",
            "and",
            "Lystra.",
            "What",
            "persecutions",
            "I",
            "endured!",
            "Yet",
            "the",
            "Lord",
            "rescued",
            "me",
            "from",
            "all",
            "of",
            "them."
        ],
        "verse_reference": "2 Timothy 3:11",
        "book": "2 Timothy",
        "chapter": "3",
        "verse": "11"
    },
    {
        "tokens": [
            "Indeed,",
            "all",
            "who",
            "desire",
            "to",
            "live",
            "godly",
            "lives",
            "in",
            "Christ",
            "Jesus",
            "will",
            "be",
            "persecuted,"
        ],
        "verse_reference": "2 Timothy 3:12",
        "book": "2 Timothy",
        "chapter": "3",
        "verse": "12"
    },
    {
        "tokens": [
            "while",
            "evil",
            "men",
            "and",
            "imposters",
            "go",
            "from",
            "bad",
            "to",
            "worse,",
            "deceiving",
            "and",
            "being",
            "deceived."
        ],
        "verse_reference": "2 Timothy 3:13",
        "book": "2 Timothy",
        "chapter": "3",
        "verse": "13"
    },
    {
        "tokens": [
            "But",
            "as",
            "for",
            "you,",
            "continue",
            "in",
            "the",
            "things",
            "you",
            "have",
            "learned",
            "and",
            "firmly",
            "believed,",
            "since",
            "you",
            "know",
            "from",
            "whom",
            "you",
            "have",
            "learned",
            "them."
        ],
        "verse_reference": "2 Timothy 3:14",
        "book": "2 Timothy",
        "chapter": "3",
        "verse": "14"
    },
    {
        "tokens": [
            "From",
            "infancy",
            "you",
            "have",
            "known",
            "the",
            "Holy",
            "Scriptures,",
            "which",
            "are",
            "able",
            "to",
            "make",
            "you",
            "wise",
            "for",
            "salvation",
            "through",
            "faith",
            "in",
            "Christ",
            "Jesus."
        ],
        "verse_reference": "2 Timothy 3:15",
        "book": "2 Timothy",
        "chapter": "3",
        "verse": "15"
    },
    {
        "tokens": [
            "All",
            "Scripture",
            "is",
            "God-breathed",
            "and",
            "is",
            "useful",
            "for",
            "instruction,",
            "for",
            "conviction,",
            "for",
            "correction,",
            "and",
            "for",
            "training",
            "in",
            "righteousness,"
        ],
        "verse_reference": "2 Timothy 3:16",
        "book": "2 Timothy",
        "chapter": "3",
        "verse": "16"
    },
    {
        "tokens": [
            "so",
            "that",
            "the",
            "man",
            "of",
            "God",
            "may",
            "be",
            "complete,",
            "fully",
            "equipped",
            "for",
            "every",
            "good",
            "work."
        ],
        "verse_reference": "2 Timothy 3:17",
        "book": "2 Timothy",
        "chapter": "3",
        "verse": "17"
    }
]